pzp_hardware/generic/control/nudge.py
pzp_hardware/generic/control/pid.py
pzp_hardware/generic/control/positioner.py
pzp_hardware/generic/control/proportional.py
pzp_hardware/generic/mixins/image_preview.py
pzp_hardware/generic/patterning/canvas.py
pzp_hardware/generic/patterning/patterns.py
pzp_hardware/lightcon/pharos.py
pzp_hardware/lightcon/topas.py
pzp_hardware/oceanview/spectrometer.py
pzp_hardware/princeton/_lightfield.py
pzp_hardware/princeton/lightfield.py
pzp_hardware/thorlabs/_powermeter.py
pzp_hardware/thorlabs/apt_piezo.py
pzp_hardware/thorlabs/apt_stage.py
pzp_hardware/thorlabs/camera.py
pzp_hardware/thorlabs/powermeter.py
pzp_hardware/thorlabs/shutter.py
pzp_hardware/vialux/dmd.py
pzp_hardware/vialux/dmd_advanced.py
pzp_hardware-0.1.0.dist-info/METADATA
pzp_hardware-0.1.0.dist-info/WHEEL
pzp_hardware-0.1.0.dist-info/licenses/LICENSE
pzp_hardware-0.1.0.dist-info/RECORD
