Metadata-Version: 2.4
Name: pzp-hardware
Version: 0.1.0
Summary: Laboratory hardware support Pieces for the puzzlepiece GUI & automation framework
Project-URL: Homepage, https://github.com/jdranczewski/pzp-hardware
Project-URL: Documentation, https://pzp-hardware.readthedocs.io
Project-URL: Bug Tracker, https://github.com/jdranczewski/pzp-hardware/issues
Author-email: Jakub Dranczewski <jakub.dranczewski@gmail.com>
License-File: LICENSE
Classifier: Development Status :: 3 - Alpha
Classifier: License :: OSI Approved :: Apache Software License
Classifier: Operating System :: OS Independent
Classifier: Programming Language :: Python :: 3
Requires-Python: >=3.7
Requires-Dist: puzzlepiece>=0.12.0
Requires-Dist: pyqtgraph
Requires-Dist: qtpy>=2.4.3
